valdec/__init__.py
valdec/data_classes.py
valdec/decorators.py
valdec/errors.py
valdec/utils.py
valdec/validator_pydantic.py
valdec/validator_validated_dc.py
valdec-1.1.0.dist-info/LICENSE
valdec-1.1.0.dist-info/METADATA
valdec-1.1.0.dist-info/WHEEL
valdec-1.1.0.dist-info/top_level.txt
valdec-1.1.0.dist-info/RECORD
